pymadx/Beam.py
pymadx/Builder.py
pymadx/Cli.py
pymadx/Data.py
pymadx/Diagrams.py
pymadx/Plot.py
pymadx/Ptc.py
pymadx/PtcAnalysis.py
pymadx/_General.py
pymadx/_Mad8.py
pymadx/__init__.py
pymadx/_version.py
pymadx/Compare/_CompareCommon.py
pymadx/Compare/_MadxMadxComparison.py
pymadx/Compare/_MadxMadxComparisonRMatrix.py
pymadx/Compare/_MadxTransportComparison.py
pymadx/Compare/__init__.py
pymadx/Convert/_Mad8ToMadx.py
pymadx/Convert/_TfsToPtc.py
pymadx/Convert/_Transport2Madx.py
pymadx/Convert/__init__.py
pymadx-3.0.2.dist-info/licenses/COPYING.txt
pymadx-3.0.2.dist-info/licenses/LICENCE.txt
pymadx-3.0.2.dist-info/METADATA
pymadx-3.0.2.dist-info/WHEEL
pymadx-3.0.2.dist-info/entry_points.txt
pymadx-3.0.2.dist-info/top_level.txt
pymadx-3.0.2.dist-info/RECORD
