Metadata-Version: 2.4
Name: pymadx
Version: 3.0.2
Summary: Package for loading MADX output.
Author-email: "JAI@RHUL" <laurie.nevay@cern.ch>
Maintainer-email: Laurie Nevay <laurie.nevay@cern.ch>
License: pymadx Copyright (C) Royal Holloway, University of London 2024
Project-URL: homepage, http://www.pp.rhul.ac.uk/bdsim/pymadx
Project-URL: documentation, http://www.pp.rhul.ac.uk/bdsim/pymadx
Project-URL: repository, https://bitbucket.org/jairhul/pymadx
Classifier: Development Status :: 5 - Production/Stable
Classifier: Intended Audience :: Developers
Classifier: Intended Audience :: Science/Research
Classifier: Operating System :: MacOS
Classifier: Operating System :: POSIX
Classifier: Operating System :: Unix
Classifier: Programming Language :: Python
Classifier: Programming Language :: Python :: 3
Classifier: Programming Language :: Python :: 3 :: Only
Classifier: Topic :: Scientific/Engineering
Classifier: Topic :: Scientific/Engineering :: Physics
Classifier: Topic :: Software Development
Requires-Python: >=3.6
License-File: LICENCE.txt
License-File: COPYING.txt
Requires-Dist: matplotlib>=3.0
Requires-Dist: numpy>=1.14
Requires-Dist: importlib-metadata
Requires-Dist: tabulate
Provides-Extra: pytransport
Requires-Dist: pytransport; extra == "pytransport"
Provides-Extra: dev
Requires-Dist: pytest; extra == "dev"
Requires-Dist: sphinx; extra == "dev"
Requires-Dist: sphinx-rtd-theme; extra == "dev"
Dynamic: license-file
